rpcmq/__init__.py
RPCmq-0.2.7.dist-info/LICENSE
RPCmq-0.2.7.dist-info/METADATA
RPCmq-0.2.7.dist-info/WHEEL
RPCmq-0.2.7.dist-info/top_level.txt
RPCmq-0.2.7.dist-info/RECORD
