Metadata-Version: 2.1
Name: RPCmq
Version: 0.2.7
Summary: Implementation of RPC by message queue call
Home-page: UNKNOWN
Author: nigowl
Author-email: nigowl@live.com
License: UNKNOWN
Platform: UNKNOWN
Classifier: Programming Language :: Python :: 3
Classifier: License :: OSI Approved :: MIT License
Classifier: Operating System :: OS Independent
Requires-Dist: pika (>=1.1.0)
